aioeway/COMPLETE_EXAMPLES.py
aioeway/__init__.py
aioeway/device_mqtt_client.py
aioeway-1.0.3.dist-info/licenses/LICENSE
aioeway-1.0.3.dist-info/METADATA
aioeway-1.0.3.dist-info/WHEEL
aioeway-1.0.3.dist-info/top_level.txt
aioeway-1.0.3.dist-info/RECORD
