Metadata-Version: 2.4
Name: aioeway
Version: 1.0.3
Summary: 一个基于异步编程的MQTT设备通信库
Home-page: https://github.com/PuuuTao/aioeway
Author: PuuuTao
Author-email: PuuuTao <kevinwang960105@gmail.com>
Project-URL: Homepage, https://github.com/PuuuTao/aioeway
Project-URL: Documentation, https://github.com/PuuuTao/aioeway/blob/main/README.md
Project-URL: Repository, https://github.com/PuuuTao/aioeway.git
Project-URL: Bug Reports, https://github.com/PuuuTao/aioeway/issues
Project-URL: Source Code, https://github.com/PuuuTao/aioeway
Keywords: mqtt,iot,device,communication,monitoring,async,asyncio
Classifier: Development Status :: 4 - Beta
Classifier: Intended Audience :: Developers
Classifier: Topic :: Software Development :: Libraries :: Python Modules
Classifier: Topic :: System :: Hardware
Classifier: Topic :: Communications
Classifier: License :: OSI Approved :: MIT License
Classifier: Programming Language :: Python :: 3
Classifier: Programming Language :: Python :: 3.7
Classifier: Programming Language :: Python :: 3.8
Classifier: Programming Language :: Python :: 3.9
Classifier: Programming Language :: Python :: 3.10
Classifier: Programming Language :: Python :: 3.11
Classifier: Programming Language :: Python :: 3.12
Classifier: Operating System :: OS Independent
Requires-Python: >=3.7
License-File: LICENSE
Requires-Dist: aiomqtt>=2.0.0
Provides-Extra: dev
Requires-Dist: pytest>=6.0; extra == "dev"
Requires-Dist: pytest-cov>=2.0; extra == "dev"
Requires-Dist: pytest-asyncio>=0.18.0; extra == "dev"
Requires-Dist: black>=21.0; extra == "dev"
Requires-Dist: flake8>=3.8; extra == "dev"
Requires-Dist: mypy>=0.910; extra == "dev"
Requires-Dist: isort>=5.0; extra == "dev"
Provides-Extra: test
Requires-Dist: pytest>=6.0; extra == "test"
Requires-Dist: pytest-cov>=2.0; extra == "test"
Requires-Dist: pytest-asyncio>=0.18.0; extra == "test"
Dynamic: author
Dynamic: home-page
Dynamic: license-file
Dynamic: requires-python
